affirmpy/__init__.py
affirmpy/api.py
affirmpy/charge.py
affirmpy/charge_event.py
affirmpy/client.py
affirmpy/response.py
affirmpy/errors/__init__.py
affirmpy/errors/authentication_error.py
affirmpy/errors/charge_error.py
affirmpy/errors/error.py
affirmpy/errors/resource_not_found_error.py
affirmpy/errors/server_error.py
Affirmpy-0.1.1.dist-info/DESCRIPTION.rst
Affirmpy-0.1.1.dist-info/METADATA
Affirmpy-0.1.1.dist-info/metadata.json
Affirmpy-0.1.1.dist-info/RECORD
Affirmpy-0.1.1.dist-info/top_level.txt
Affirmpy-0.1.1.dist-info/WHEEL
