Metadata-Version: 2.0
Name: Affirmpy
Version: 0.1.1
Summary: A Python API wrapper for Affirm
Home-page: https://github.com/royels/Affirmpy
Author: Rohan Yelsangikar
Author-email: ryelsang@ucsd.edu
License: MIT
Keywords: Affirm API wrapper python fun
Platform: UNKNOWN
Classifier: Development Status :: 3 - Alpha
Classifier: Intended Audience :: Developers
Classifier: Topic :: Software Development :: Build Tools
Classifier: License :: OSI Approved :: MIT License
Classifier: Programming Language :: Python :: 2.7
Requires-Dist: requests
